docker_image_builder/__init__.py
docker_image_builder/__main__.py
docker_image_builder/args.py
docker_image_builder/docker_helper.py
docker_image_builder/docker_image_builder.py
docker_image_builder-0.1.3.dist-info/DESCRIPTION.rst
docker_image_builder-0.1.3.dist-info/METADATA
docker_image_builder-0.1.3.dist-info/RECORD
docker_image_builder-0.1.3.dist-info/WHEEL
docker_image_builder-0.1.3.dist-info/entry_points.txt
docker_image_builder-0.1.3.dist-info/metadata.json
docker_image_builder-0.1.3.dist-info/top_level.txt
