Metadata-Version: 2.0
Name: docker-image-builder
Version: 0.1.3
Summary: Helper for easily manage the images stack
Home-page: https://github.com/lbacik/docker-image-builder
Author: Lukasz Bacik
Author-email: mail@luka.sh
License: GPLv2
Keywords: docker development
Platform: UNKNOWN
Classifier: Development Status :: 3 - Alpha
Classifier: Intended Audience :: Developers
Classifier: Topic :: Software Development :: Build Tools
Classifier: License :: OSI Approved :: GNU General Public License v2 (GPLv2)
Classifier: Programming Language :: Python :: 3
Requires-Dist: docker
Requires-Dist: dockerfile-parse
Provides-Extra: dev
Requires-Dist: check-manifest; extra == 'dev'
Provides-Extra: test
Requires-Dist: coverage; extra == 'test'
